Experiment/Main.py
Experiment/__init__.py
thesis_experiment_test-0.4.10.dist-info/METADATA
thesis_experiment_test-0.4.10.dist-info/WHEEL
thesis_experiment_test-0.4.10.dist-info/top_level.txt
thesis_experiment_test-0.4.10.dist-info/RECORD
