Metadata-Version: 2.1
Name: thesis-experiment-test
Version: 0.4.10
Author: Wouter Peere
Classifier: Programming Language :: Python :: 3
Classifier: License :: OSI Approved :: BSD License
Classifier: Operating System :: OS Independent
Requires-Python: >=3.7
Requires-Dist: numpy >=1.23.1
